README.md
setup.py
cfpusher/__init__.py
cfpusher/__main__.py
cfpusher/confluence.lua
confluence_pusher.egg-info/PKG-INFO
confluence_pusher.egg-info/SOURCES.txt
confluence_pusher.egg-info/dependency_links.txt
confluence_pusher.egg-info/entry_points.txt
confluence_pusher.egg-info/requires.txt
confluence_pusher.egg-info/top_level.txt