Metadata-Version: 2.1
Name: confluence-pusher
Version: 0.1.567
Summary: A tool to convert and upload markdown documents into Atlassian Confluence
Home-page: https://www.servian.com/
License: MIT
Project-URL: Source Code, https://github.com/servian/confluence-pusher
Keywords: confluence markdown
Platform: UNKNOWN
Classifier: Programming Language :: Python :: 3
Classifier: License :: OSI Approved :: MIT License
Classifier: Operating System :: OS Independent
Requires-Python: >=3.6
